pysqlcipher3static.libs/libcrypto-d3570994.so.1.0.2k
pysqlcipher3/README.md
pysqlcipher3/dbapi2.py
pysqlcipher3/_sqlite3.cpython-310-x86_64-linux-gnu.so
pysqlcipher3/__init__.py
pysqlcipher3/c/row.c
pysqlcipher3/c/cache.c
pysqlcipher3/c/row.h
pysqlcipher3/c/statement.h
pysqlcipher3/c/microprotocols.c
pysqlcipher3/c/util.c
pysqlcipher3/c/module.h
pysqlcipher3/c/util.h
pysqlcipher3/c/statement.c
pysqlcipher3/c/cursor.c
pysqlcipher3/c/cursor.h
pysqlcipher3/c/module.c
pysqlcipher3/c/microprotocols.h
pysqlcipher3/c/prepare_protocol.c
pysqlcipher3/c/cache.h
pysqlcipher3/c/connection.c
pysqlcipher3/c/prepare_protocol.h
pysqlcipher3/c/connection.h
pysqlcipher3/c/sqlcipher/README.md
pysqlcipher3/c/sqlcipher/sqlite3.c
pysqlcipher3/c/sqlcipher/sqlite3.h
pysqlcipher3static-2.0.1.dist-info/WHEEL
pysqlcipher3static-2.0.1.dist-info/LICENSE
pysqlcipher3static-2.0.1.dist-info/top_level.txt
pysqlcipher3static-2.0.1.dist-info/RECORD
pysqlcipher3static-2.0.1.dist-info/METADATA
